emmel/__init__.py
emmel-0.0.1.dist-info/METADATA
emmel-0.0.1.dist-info/WHEEL
emmel-0.0.1.dist-info/RECORD
