Metadata-Version: 2.4
Name: emmel
Version: 0.0.1
Summary: M language (Power Query) parser and evaluator
Project-URL: repository, https://github.com/onnovalkering/emmel
License-Expression: MIT
Requires-Python: >=3.11
